README.md
setup.py
loggerutils/__init__.py
loggerutils/formatter.py
loggerutils/tests.py
loggerutils.egg-info/PKG-INFO
loggerutils.egg-info/SOURCES.txt
loggerutils.egg-info/dependency_links.txt
loggerutils.egg-info/not-zip-safe
loggerutils.egg-info/requires.txt
loggerutils.egg-info/top_level.txt